ibmpa_provider/__init__.py
ibmpa_provider/hooks/__init__.py
ibmpa_provider/hooks/ibmpa.py
ibmpa_provider/operators/__init__.py
ibmpa_provider/operators/ibmpa.py
airflow_provider_ibmpa-0.0.5.dist-info/METADATA
airflow_provider_ibmpa-0.0.5.dist-info/WHEEL
airflow_provider_ibmpa-0.0.5.dist-info/entry_points.txt
airflow_provider_ibmpa-0.0.5.dist-info/top_level.txt
airflow_provider_ibmpa-0.0.5.dist-info/RECORD
